stss/__init__.py
stss/st.py
stss/st2d.py
stss/st2d_cupy.py
stss/st3d.py
stss/st3d_cupy.py
stss/st_cupy.py
stss/util.py
stss/util_cupy.py
stss-0.1.0.dist-info/LICENSE
stss-0.1.0.dist-info/METADATA
stss-0.1.0.dist-info/WHEEL
stss-0.1.0.dist-info/top_level.txt
stss-0.1.0.dist-info/RECORD
