Metadata-Version: 2.1
Name: stss
Version: 0.1.0
Summary: 2D and 3D structure tensor scale space implementation for Python.
Author-email: Pawel Tomasz Pieta <papi@dtu.dk>
License: MIT License
Project-URL: Homepage, https://github.com/PaPieta/stss
Project-URL: Issues, https://github.com/PaPieta/stss/issues
Classifier: Programming Language :: Python :: 3
Classifier: Operating System :: OS Independent
Requires-Python: >=3.8
License-File: LICENSE
Requires-Dist: numpy
Requires-Dist: scipy
